qtextra/__init__.py
qtextra/_pydantic_compat.py
qtextra/auto.py
qtextra/event_loop.py
qtextra/helpers.py
qtextra/icons.py
qtextra/mixins.py
qtextra/py.typed
qtextra/typing.py
qtextra/assets/__init__.py
qtextra/assets/gifs/loading-circle.gif
qtextra/assets/gifs/loading-dots.gif
qtextra/assets/gifs/loading-infinity.gif
qtextra/assets/gifs/loading-oval.gif
qtextra/assets/gifs/loading-square.gif
qtextra/assets/stylesheets/00_base.qss
qtextra/assets/stylesheets/01_buttons.qss
qtextra/assets/stylesheets/01_labels.qss
qtextra/assets/stylesheets/02_icons.qss
qtextra/assets/stylesheets/03_qta.qss
qtextra/assets/stylesheets/04_custom.qss
qtextra/assets/stylesheets/04_notification.qss
qtextra/assets/stylesheets/04_statusbar.qss
qtextra/assets/stylesheets/04_tag.qss
qtextra/assets/stylesheets/04_toast.qss
qtextra/assets/stylesheets/04_tutorial.qss
qtextra/assets/stylesheets/07_queue.qss
qtextra/config/__init__.py
qtextra/config/config.py
qtextra/config/events.py
qtextra/config/theme.py
qtextra/custom/__init__.py
qtextra/custom/qt_directory_manager.py
qtextra/dialogs/__init__.py
qtextra/dialogs/qt_changelog.py
qtextra/dialogs/qt_close_window.py
qtextra/dialogs/qt_color_dialog.py
qtextra/dialogs/qt_confirm.py
qtextra/dialogs/qt_console.py
qtextra/dialogs/qt_dev.py
qtextra/dialogs/qt_info.py
qtextra/dialogs/qt_info_popup.py
qtextra/dialogs/qt_logger.py
qtextra/dialogs/qt_sysinfo.py
qtextra/dialogs/qt_text_replace.py
qtextra/dialogs/qt_theme_sample.py
qtextra/dialogs/qt_wait.py
qtextra/dialogs/sentry/__init__.py
qtextra/dialogs/sentry/feedback.py
qtextra/dialogs/sentry/telemetry.py
qtextra/dialogs/sentry/utilities.py
qtextra/queue/__init__.py
qtextra/queue/cli_qprocess.py
qtextra/queue/cli_queue.py
qtextra/queue/info.py
qtextra/queue/item.py
qtextra/queue/popup.py
qtextra/queue/queue_widget.py
qtextra/queue/task.py
qtextra/queue/utilities.py
qtextra/utils/__init__.py
qtextra/utils/appdirs.py
qtextra/utils/color.py
qtextra/utils/context.py
qtextra/utils/dev.py
qtextra-0.1.6.dist-info/METADATA
qtextra-0.1.6.dist-info/WHEEL
qtextra-0.1.6.dist-info/licenses/LICENSE
qtextra-0.1.6.dist-info/RECORD
