Metadata-Version: 2.4
Name: qtextra
Version: 0.1.6
Summary: Extra widgets for Qt
Project-URL: homepage, https://github.com/lukasz-migas/qtextra
Project-URL: repository, https://github.com/lukasz-migas/qtextra
Author-email: "Lukasz G. Migas" <lukas.migas@yahoo.com>
License: BSD 3-Clause License
License-File: LICENSE
Classifier: Development Status :: 3 - Alpha
Classifier: License :: OSI Approved :: BSD License
Classifier: Natural Language :: English
Classifier: Programming Language :: Python :: 3
Classifier: Programming Language :: Python :: 3.10
Classifier: Programming Language :: Python :: 3.11
Classifier: Programming Language :: Python :: 3.12
Classifier: Programming Language :: Python :: 3.13
Classifier: Typing :: Typed
Requires-Python: >=3.10
Requires-Dist: appdirs
Requires-Dist: koyo
Requires-Dist: numpy
Requires-Dist: psygnal>=0.14.2; python_version <= '3.9'
Requires-Dist: psygnal>=0.15.0; python_version >= '3.10'
Requires-Dist: pydantic-extra-types
Requires-Dist: pydantic>2
Requires-Dist: qtawesome
Requires-Dist: qtpy
Requires-Dist: superqt>=0.7.1
Provides-Extra: all
Requires-Dist: ipykernel>=5.2.0; extra == 'all'
Requires-Dist: pyqt6; (platform_system != 'Windows') and extra == 'all'
Requires-Dist: pyqt6>6.9.0; (platform_system == 'Windows') and extra == 'all'
Requires-Dist: qtconsole!=4.7.6,!=5.4.2,>=4.5.1; extra == 'all'
Requires-Dist: sentry-sdk>2; extra == 'all'
Provides-Extra: console
Requires-Dist: ipykernel>=5.2.0; extra == 'console'
Requires-Dist: qtconsole!=4.7.6,!=5.4.2,>=4.5.1; extra == 'console'
Provides-Extra: dev
Requires-Dist: check-manifest; extra == 'dev'
Requires-Dist: ipython; extra == 'dev'
Requires-Dist: mypy; extra == 'dev'
Requires-Dist: pdbpp; extra == 'dev'
Requires-Dist: pre-commit; extra == 'dev'
Requires-Dist: pytest-cov; extra == 'dev'
Requires-Dist: pytest-pretty; extra == 'dev'
Requires-Dist: pytest-qt; extra == 'dev'
Requires-Dist: pytest>=8.1; extra == 'dev'
Requires-Dist: qtreload; extra == 'dev'
Requires-Dist: rich; extra == 'dev'
Requires-Dist: ruff; extra == 'dev'
Provides-Extra: pyqt5
Requires-Dist: pyqt5; extra == 'pyqt5'
Provides-Extra: pyqt6
Requires-Dist: pyqt6; (platform_system != 'Windows') and extra == 'pyqt6'
Requires-Dist: pyqt6>6.9.0; (platform_system == 'Windows') and extra == 'pyqt6'
Provides-Extra: pyside2
Requires-Dist: pyside2; extra == 'pyside2'
Provides-Extra: pyside6
Requires-Dist: pyside6; (platform_system != 'Windows') and extra == 'pyside6'
Requires-Dist: pyside6>6.9.0; (platform_system == 'Windows') and extra == 'pyside6'
Provides-Extra: reload
Requires-Dist: qtreload; extra == 'reload'
Provides-Extra: sentry
Requires-Dist: sentry-sdk>2; extra == 'sentry'
Provides-Extra: test
Requires-Dist: pytest-cov; extra == 'test'
Requires-Dist: pytest-pretty; extra == 'test'
Requires-Dist: pytest-qt; extra == 'test'
Requires-Dist: pytest>=8.1; extra == 'test'
